Geometry/Vectors3D.py
Geometry/__init__.py
Geometry/encoder_wheel.py
NumericalDE/FiniteDifference1D.py
NumericalDE/Mesh.py
NumericalDE/__init__.py
NumericalDE/demo/FDE1D_direchlet_NL_Poisson.py
NumericalDE/demo/FDE1D_direchlet_NL_Poisson_mesh.py
NumericalDE/demo/FDE1D_dirichlet_NL_Poisson_AMR.py
NumericalDE/demo/FDE1D_dirichlet_Poisson.py
NumericalDE/demo/FDE1D_dirichlet_Poisson_AMR.py
NumericalDE/demo/FDE1D_neuman_Poisson.py
NumericalDE/demo/Meshes1D_demo.py
NumericalDE/demo/__init__.py
Potential/Potential_1D.py
Potential/Potential_3D.py
Potential/__init__.py
ProjectManager/ProjectManager.py
ProjectManager/__init__.py
ProjectManager/numeric_operations.py
Schottky/Helpers.py
Schottky/__init__.py
Schottky/_version.py
Schottky/Diode/Kinetics.py
Schottky/Diode/Poisson.py
Schottky/Diode/SchottkyDiode.py
Schottky/Diode/Visual.py
Schottky/Diode/__init__.py
Schottky/Metal/__init__.py
Schottky/Notation/__init__.py
Schottky/Reference/__init__.py
Schottky/Semiconductor/BondingInterface.py
Schottky/Semiconductor/Dislocation.py
Schottky/Semiconductor/Dopant.py
Schottky/Semiconductor/Semiconductor.py
Schottky/Semiconductor/Trap.py
Schottky/Semiconductor/__init__.py
Schottky-0.0.1.dist-info/METADATA
Schottky-0.0.1.dist-info/RECORD
Schottky-0.0.1.dist-info/WHEEL
Schottky-0.0.1.dist-info/top_level.txt
